mandic_panoptes/__init__.py
mandic_panoptes/panoptesctl.py
mandic_panoptes/aws/__init__.py
mandic_panoptes/aws/analysis.py
mandic_panoptes/aws/attached.py
mandic_panoptes/aws/authentication.py
mandic_panoptes/aws/exceptions.py
mandic_panoptes/aws/output.py
mandic_panoptes/aws/whitelist.py
mandic_panoptes/cli/__init__.py
mandic_panoptes/cli/aws.py
mandic_panoptes/cli/gcp.py
mandic_panoptes/generic/__init__.py
mandic_panoptes/generic/helpers.py
mandic_panoptes/generic/output.py
mandic_panoptes-0.6.0.dist-info/LICENSE
mandic_panoptes-0.6.0.dist-info/METADATA
mandic_panoptes-0.6.0.dist-info/WHEEL
mandic_panoptes-0.6.0.dist-info/entry_points.txt
mandic_panoptes-0.6.0.dist-info/top_level.txt
mandic_panoptes-0.6.0.dist-info/RECORD
