Metadata-Version: 2.1
Name: mandic-panoptes
Version: 0.6.0
Summary: The multi cloud security group analyzer
Home-page: https://gitlab.com/rivendel-cmp/panoptes
Author: Bryan Cruz
Author-email: bryan.cruz@mandic.net.br
License: LICENSE
Keywords: panoptes aws security analysis cloud devops
Platform: UNKNOWN
Requires-Python: >=3.6
Requires-Dist: boto3 (==1.9.28)
Requires-Dist: click (==7.0)
Requires-Dist: colorama (==0.4.0)
Requires-Dist: PyYAML (==3.13)
Requires-Dist: Jinja2 (==2.10)
